MANIFEST.in
license.txt
requirements.txt
setup.py
src/MurmurHash3.c
src/MurmurHash3.h
src/_hydra.c
src/_hydra.pyx
src/hydra.py
src/mmap_writer.c
src/mmap_writer.h
src/Hydra.egg-info/PKG-INFO
src/Hydra.egg-info/SOURCES.txt
src/Hydra.egg-info/dependency_links.txt
src/Hydra.egg-info/not-zip-safe
src/Hydra.egg-info/top_level.txt
tests/helpers.py
tests/test_bloom.py
tests/test_mmapbitarray.py
tests/test_murmur.py
tests/timeit.py