Metadata-Version: 1.0
Name: Hydra
Version: 2.3
Summary: A high performance persistent bloom filter
Home-page: http://github.com/crankycoder/Hydra
Author: Victor Ng
Author-email: crankycoder@gmail.com
License: MIT License
Platform: UNKNOWN
